<?xml version="1.0" encoding="UTF-8"?>
<metadata xml:lang="en"><Esri><CreaDate>20160624</CreaDate><CreaTime>14531400</CreaTime><ArcGISFormat>1.0</ArcGISFormat><SyncOnce>TRUE</SyncOnce><DataProperties><lineage><Process ToolSource="c:\program files (x86)\arcgis\desktop10.3\ArcToolbox\Toolboxes\Spatial Analyst Tools.tbx\KernelDensity" Date="20160624" Time="145314">KernelDensity dest_10 NONE D:\Xu_Data\DiDi_IACP\GIS\kernel_density\dest_10.tif 30 # SQUARE_KILOMETERS DENSITIES PLANAR</Process></lineage></DataProperties></Esri></metadata>
